{
  "ok": true,
  "proofType": "MLB_POSTDEPLOY_SETTLEMENT_INTEGRITY",
  "createdAtUtc": "2026-07-17T20:39:30.286256+00:00",
  "greenDeploymentCutoffUtc": "2026-07-13T00:20:03+00:00",
  "postDeployLockedRowsInWindow": 1,
  "postDeployCompletedRowsInWindow": 1,
  "postDeployGradedRowsInWindow": 1,
  "failureCount": 0,
  "failures": [],
  "status": "VERIFIED",
  "policy": "Every completed post-deployment row must be eligible for the authoritative clean cohort. Final labels are joined after completion and the exact immutable pregame vector retains blank outcome labels."
}
