{
  "ok": true,
  "proofType": "MLB_ROLLING_24H_AUDIT",
  "createdAt": "2026-06-30T14:27:06.872501+00:00",
  "sport": "mlb",
  "windowHours": 24,
  "summary": {
    "windowHours": 24,
    "targetAccuracyPct": 90.0,
    "completedFinalGames": 13,
    "gradedPredictionCount": 13,
    "missingPredictionCount": 0,
    "optimizedPickCount": 13,
    "optimizedCorrect": 7,
    "optimizedWrong": 6,
    "rolling24hOptimizedAccuracyPct": 53.85,
    "rolling24hTargetMet": false,
    "winnerOptimizerAppliedCount": 0,
    "winnerOptimizerFlipCount": 0,
    "allScoredPickAccuracyPct": 53.85,
    "actionablePickCount": 13,
    "actionableCorrect": 7,
    "actionableWrong": 6,
    "rolling24hActionableAccuracyPct": 53.85
  },
  "scoreLearning": {
    "tagStats": {
      "BOOK_DIVERGENCE": {
        "count": 6,
        "correct": 3,
        "accuracyPct": 50.0
      },
      "REVERSAL": {
        "count": 13,
        "correct": 7,
        "accuracyPct": 53.85
      },
      "RUN_LINE_MOVEMENT": {
        "count": 11,
        "correct": 6,
        "accuracyPct": 54.55
      },
      "RUN_LINE_CONFIRMATION": {
        "count": 4,
        "correct": 3,
        "accuracyPct": 75.0
      },
      "STEAM": {
        "count": 10,
        "correct": 6,
        "accuracyPct": 60.0
      },
      "BOOK_AGREEMENT": {
        "count": 5,
        "correct": 3,
        "accuracyPct": 60.0
      },
      "COMPRESSED_MARKET": {
        "count": 1,
        "correct": 0,
        "accuracyPct": 0.0
      }
    },
    "tagComboStats": {
      "BOOK_DIVERGENCE+REVERSAL+RUN_LINE_MOVEMENT": {
        "count": 1,
        "correct": 0,
        "accuracyPct": 0.0
      },
      "BOOK_DIVERGENCE+REVERSAL+RUN_LINE_CONFIRMATION+RUN_LINE_MOVEMENT+STEAM": {
        "count": 2,
        "correct": 2,
        "accuracyPct": 100.0
      },
      "BOOK_AGREEMENT+REVERSAL+RUN_LINE_MOVEMENT+STEAM": {
        "count": 1,
        "correct": 1,
        "accuracyPct": 100.0
      },
      "BOOK_AGREEMENT+REVERSAL+RUN_LINE_CONFIRMATION+RUN_LINE_MOVEMENT+STEAM": {
        "count": 2,
        "correct": 1,
        "accuracyPct": 50.0
      },
      "BOOK_DIVERGENCE+REVERSAL+RUN_LINE_MOVEMENT+STEAM": {
        "count": 3,
        "correct": 1,
        "accuracyPct": 33.33
      },
      "REVERSAL+RUN_LINE_MOVEMENT+STEAM": {
        "count": 2,
        "correct": 1,
        "accuracyPct": 50.0
      },
      "BOOK_AGREEMENT+REVERSAL": {
        "count": 1,
        "correct": 1,
        "accuracyPct": 100.0
      },
      "BOOK_AGREEMENT+COMPRESSED_MARKET+REVERSAL": {
        "count": 1,
        "correct": 0,
        "accuracyPct": 0.0
      }
    },
    "confidenceStats": {
      "Pass": {
        "count": 5,
        "correct": 1,
        "accuracyPct": 20.0
      },
      "Premium": {
        "count": 8,
        "correct": 6,
        "accuracyPct": 75.0
      }
    },
    "optimizerFlipStats": {
      "NOT_FLIPPED": {
        "count": 13,
        "correct": 7,
        "accuracyPct": 53.85
      }
    },
    "adjustments": {
      "tagScoreAdjustments": {
        "BOOK_DIVERGENCE": 0.0,
        "REVERSAL": 0.21,
        "RUN_LINE_MOVEMENT": 0.25,
        "RUN_LINE_CONFIRMATION": 1.39,
        "STEAM": 0.56,
        "BOOK_AGREEMENT": 0.56,
        "COMPRESSED_MARKET": -0.75
      },
      "tagComboScoreAdjustments": {
        "BOOK_DIVERGENCE+REVERSAL+RUN_LINE_MOVEMENT": -0.75,
        "BOOK_DIVERGENCE+REVERSAL+RUN_LINE_CONFIRMATION+RUN_LINE_MOVEMENT+STEAM": 4.17,
        "BOOK_AGREEMENT+REVERSAL+RUN_LINE_MOVEMENT+STEAM": 0.75,
        "BOOK_AGREEMENT+REVERSAL+RUN_LINE_CONFIRMATION+RUN_LINE_MOVEMENT+STEAM": 0.0,
        "BOOK_DIVERGENCE+REVERSAL+RUN_LINE_MOVEMENT+STEAM": -1.39,
        "REVERSAL+RUN_LINE_MOVEMENT+STEAM": 0.0,
        "BOOK_AGREEMENT+REVERSAL": 0.75,
        "BOOK_AGREEMENT+COMPRESSED_MARKET+REVERSAL": -0.75
      }
    },
    "policy": "Learning is optimized for correct team-winner selection on every game. Tag and tag-combination adjustments are bounded to avoid overfitting one day."
  },
  "rows": [
    {
      "id": "da58edb8a6932f91a04f398f83ed0658",
      "gameKeyBase": "chicago white sox|baltimore orioles",
      "homeTeam": "Baltimore Orioles",
      "awayTeam": "Chicago White Sox",
      "matchup": "Chicago White Sox at Baltimore Orioles",
      "commenceTime": "2026-06-29T22:36:00Z",
      "slateDateEt": "2026-06-29",
      "homeScore": 2,
      "awayScore": 8,
      "winner": "Chicago White Sox",
      "margin": 6,
      "totalRuns": 10,
      "completed": true,
      "status": "GRADED",
      "predictedWinner": "Baltimore Orioles",
      "predictedSide": "home",
      "score": "0",
      "winProbabilityPct": "5",
      "confidenceTier": "Pass",
      "tags": [
        "BOOK_DIVERGENCE",
        "REVERSAL",
        "RUN_LINE_MOVEMENT"
      ],
      "selectionBeforeWinnerOptimizer": null,
      "individualWinnerOptimized": null,
      "optimizerFlippedPick": null,
      "winnerOptimizer": null,
      "homeSignal": {
        "probStart": "0.55061",
        "probLatest": "0.55121",
        "side": "home",
        "averageAmericanOdds": "-142.5",
        "bookCount": "8",
        "delta": "0.00059",
        "latestGap": "0.10242",
        "runLineMovement": "14.114",
        "team": "Baltimore Orioles",
        "tags": [
          "BOOK_DIVERGENCE",
          "REVERSAL",
          "RUN_LINE_MOVEMENT"
        ],
        "score": "0",
        "winProbability": "0.05",
        "marketConsensusProbability": "0.55121",
        "bookDivergence": "0.04898",
        "reversalCount": "8",
        "winProbabilityPct": "5"
      },
      "awaySignal": {
        "probStart": "0.44939",
        "probLatest": "0.44879",
        "side": "away",
        "averageAmericanOdds": "84.5",
        "bookCount": "8",
        "delta": "-0.00059",
        "latestGap": "0.10242",
        "runLineMovement": "-43.67",
        "team": "Chicago White Sox",
        "tags": [
          "BOOK_DIVERGENCE",
          "REVERSAL",
          "RUN_LINE_MOVEMENT"
        ],
        "score": "0",
        "winProbability": "0.05",
        "marketConsensusProbability": "0.44879",
        "bookDivergence": "0.04898",
        "reversalCount": "8",
        "winProbabilityPct": "5"
      },
      "correct": false
    },
    {
      "id": "e82ac8c2a7cc7adb87a3de75b787a898",
      "gameKeyBase": "pittsburgh pirates|philadelphia phillies",
      "homeTeam": "Philadelphia Phillies",
      "awayTeam": "Pittsburgh Pirates",
      "matchup": "Pittsburgh Pirates at Philadelphia Phillies",
      "commenceTime": "2026-06-29T22:41:00Z",
      "slateDateEt": "2026-06-29",
      "homeScore": 7,
      "awayScore": 11,
      "winner": "Pittsburgh Pirates",
      "margin": 4,
      "totalRuns": 18,
      "completed": true,
      "status": "GRADED",
      "predictedWinner": "Pittsburgh Pirates",
      "predictedSide": "away",
      "score": "100",
      "winProbabilityPct": "95",
      "confidenceTier": "Premium",
      "tags": [
        "BOOK_DIVERGENCE",
        "REVERSAL",
        "RUN_LINE_CONFIRMATION",
        "RUN_LINE_MOVEMENT",
        "STEAM"
      ],
      "selectionBeforeWinnerOptimizer": null,
      "individualWinnerOptimized": null,
      "optimizerFlippedPick": null,
      "winnerOptimizer": null,
      "homeSignal": {
        "probStart": "0.51019",
        "probLatest": "0.09724",
        "side": "home",
        "averageAmericanOdds": "1941.67",
        "bookCount": "3",
        "delta": "-0.41295",
        "latestGap": "0.80553",
        "runLineMovement": "-94.364",
        "team": "Philadelphia Phillies",
        "tags": [
          "BOOK_DIVERGENCE",
          "RESISTANCE",
          "REVERSAL",
          "RUN_LINE_MOVEMENT"
        ],
        "score": "0",
        "winProbability": "0.05",
        "marketConsensusProbability": "0.09724",
        "bookDivergence": "0.19169",
        "reversalCount": "9",
        "winProbabilityPct": "5"
      },
      "awaySignal": {
        "probStart": "0.48981",
        "probLatest": "0.90276",
        "side": "away",
        "averageAmericanOdds": "-20151.67",
        "bookCount": "3",
        "delta": "0.41295",
        "latestGap": "0.80553",
        "runLineMovement": "-61.788",
        "team": "Pittsburgh Pirates",
        "tags": [
          "BOOK_DIVERGENCE",
          "REVERSAL",
          "RUN_LINE_CONFIRMATION",
          "RUN_LINE_MOVEMENT",
          "STEAM"
        ],
        "score": "100",
        "winProbability": "0.95",
        "marketConsensusProbability": "0.90276",
        "bookDivergence": "0.19169",
        "reversalCount": "9",
        "winProbabilityPct": "95"
      },
      "correct": true
    },
    {
      "id": "894c544f93b835c08a74ade08d26888f",
      "gameKeyBase": "new york mets|toronto blue jays",
      "homeTeam": "Toronto Blue Jays",
      "awayTeam": "New York Mets",
      "matchup": "New York Mets at Toronto Blue Jays",
      "commenceTime": "2026-06-29T23:08:00Z",
      "slateDateEt": "2026-06-29",
      "homeScore": 2,
      "awayScore": 1,
      "winner": "Toronto Blue Jays",
      "margin": 1,
      "totalRuns": 3,
      "completed": true,
      "status": "GRADED",
      "predictedWinner": "Toronto Blue Jays",
      "predictedSide": "home",
      "score": "100",
      "winProbabilityPct": "95",
      "confidenceTier": "Premium",
      "tags": [
        "BOOK_DIVERGENCE",
        "REVERSAL",
        "RUN_LINE_CONFIRMATION",
        "RUN_LINE_MOVEMENT",
        "STEAM"
      ],
      "selectionBeforeWinnerOptimizer": null,
      "individualWinnerOptimized": null,
      "optimizerFlippedPick": null,
      "winnerOptimizer": null,
      "homeSignal": {
        "probStart": "0.53856",
        "probLatest": "0.88119",
        "side": "home",
        "averageAmericanOdds": "-1743.5",
        "bookCount": "8",
        "delta": "0.34263",
        "latestGap": "0.76238",
        "runLineMovement": "-6118.159",
        "team": "Toronto Blue Jays",
        "tags": [
          "BOOK_DIVERGENCE",
          "REVERSAL",
          "RUN_LINE_CONFIRMATION",
          "RUN_LINE_MOVEMENT",
          "STEAM"
        ],
        "score": "100",
        "winProbability": "0.95",
        "marketConsensusProbability": "0.88119",
        "bookDivergence": "0.07586",
        "reversalCount": "1",
        "winProbabilityPct": "95"
      },
      "awaySignal": {
        "probStart": "0.46144",
        "probLatest": "0.11881",
        "side": "away",
        "averageAmericanOdds": "738.12",
        "bookCount": "8",
        "delta": "-0.34263",
        "latestGap": "0.76238",
        "runLineMovement": "1477.523",
        "team": "New York Mets",
        "tags": [
          "BOOK_DIVERGENCE",
          "RESISTANCE",
          "REVERSAL",
          "RUN_LINE_MOVEMENT"
        ],
        "score": "0",
        "winProbability": "0.05",
        "marketConsensusProbability": "0.11881",
        "bookDivergence": "0.07586",
        "reversalCount": "1",
        "winProbabilityPct": "5"
      },
      "correct": true
    },
    {
      "id": "140bee4546319ca4bfbaa6d6bf8d2016",
      "gameKeyBase": "detroit tigers|new york yankees",
      "homeTeam": "New York Yankees",
      "awayTeam": "Detroit Tigers",
      "matchup": "Detroit Tigers at New York Yankees",
      "commenceTime": "2026-06-29T23:10:00Z",
      "slateDateEt": "2026-06-29",
      "homeScore": 3,
      "awayScore": 7,
      "winner": "Detroit Tigers",
      "margin": 4,
      "totalRuns": 10,
      "completed": true,
      "status": "GRADED",
      "predictedWinner": "Detroit Tigers",
      "predictedSide": "away",
      "score": "100",
      "winProbabilityPct": "95",
      "confidenceTier": "Premium",
      "tags": [
        "BOOK_AGREEMENT",
        "REVERSAL",
        "RUN_LINE_MOVEMENT",
        "STEAM"
      ],
      "selectionBeforeWinnerOptimizer": null,
      "individualWinnerOptimized": null,
      "optimizerFlippedPick": null,
      "winnerOptimizer": null,
      "homeSignal": {
        "probStart": "0.56879",
        "probLatest": "0.0315",
        "side": "home",
        "averageAmericanOdds": "3000",
        "bookCount": "1",
        "delta": "-0.53728",
        "latestGap": "0.937",
        "runLineMovement": "-25.364",
        "team": "New York Yankees",
        "tags": [
          "BOOK_AGREEMENT",
          "RESISTANCE",
          "REVERSAL",
          "RUN_LINE_MOVEMENT"
        ],
        "score": "0",
        "winProbability": "0.05",
        "marketConsensusProbability": "0.0315",
        "bookDivergence": "0",
        "reversalCount": "4",
        "winProbabilityPct": "5"
      },
      "awaySignal": {
        "probStart": "0.43121",
        "probLatest": "0.9685",
        "side": "away",
        "averageAmericanOdds": "-12000",
        "bookCount": "1",
        "delta": "0.53728",
        "latestGap": "0.937",
        "runLineMovement": "14.273",
        "team": "Detroit Tigers",
        "tags": [
          "BOOK_AGREEMENT",
          "REVERSAL",
          "RUN_LINE_MOVEMENT",
          "STEAM"
        ],
        "score": "100",
        "winProbability": "0.95",
        "marketConsensusProbability": "0.9685",
        "bookDivergence": "0",
        "reversalCount": "4",
        "winProbabilityPct": "95"
      },
      "correct": true
    },
    {
      "id": "ca341550fc4220b9ee976aaa8bc933db",
      "gameKeyBase": "washington nationals|boston red sox",
      "homeTeam": "Boston Red Sox",
      "awayTeam": "Washington Nationals",
      "matchup": "Washington Nationals at Boston Red Sox",
      "commenceTime": "2026-06-29T23:11:00Z",
      "slateDateEt": "2026-06-29",
      "homeScore": 6,
      "awayScore": 3,
      "winner": "Boston Red Sox",
      "margin": 3,
      "totalRuns": 9,
      "completed": true,
      "status": "GRADED",
      "predictedWinner": "Boston Red Sox",
      "predictedSide": "home",
      "score": "100",
      "winProbabilityPct": "95",
      "confidenceTier": "Premium",
      "tags": [
        "BOOK_AGREEMENT",
        "REVERSAL",
        "RUN_LINE_CONFIRMATION",
        "RUN_LINE_MOVEMENT",
        "STEAM"
      ],
      "selectionBeforeWinnerOptimizer": null,
      "individualWinnerOptimized": null,
      "optimizerFlippedPick": null,
      "winnerOptimizer": null,
      "homeSignal": {
        "probStart": "0.61859",
        "probLatest": "0.9775",
        "side": "home",
        "averageAmericanOdds": "-30000",
        "bookCount": "2",
        "delta": "0.35891",
        "latestGap": "0.95499",
        "runLineMovement": "-1915.545",
        "team": "Boston Red Sox",
        "tags": [
          "BOOK_AGREEMENT",
          "REVERSAL",
          "RUN_LINE_CONFIRMATION",
          "RUN_LINE_MOVEMENT",
          "STEAM"
        ],
        "score": "100",
        "winProbability": "0.95",
        "marketConsensusProbability": "0.9775",
        "bookDivergence": "0.01269",
        "reversalCount": "4",
        "winProbabilityPct": "95"
      },
      "awaySignal": {
        "probStart": "0.38141",
        "probLatest": "0.0225",
        "side": "away",
        "averageAmericanOdds": "4650",
        "bookCount": "2",
        "delta": "-0.35891",
        "latestGap": "0.95499",
        "runLineMovement": "999.864",
        "team": "Washington Nationals",
        "tags": [
          "BOOK_AGREEMENT",
          "RESISTANCE",
          "REVERSAL",
          "RUN_LINE_MOVEMENT"
        ],
        "score": "0",
        "winProbability": "0.05",
        "marketConsensusProbability": "0.0225",
        "bookDivergence": "0.01269",
        "reversalCount": "4",
        "winProbabilityPct": "5"
      },
      "correct": true
    },
    {
      "id": "74432b663df15c5695ec62a802768a60",
      "gameKeyBase": "texas rangers|cleveland guardians",
      "homeTeam": "Cleveland Guardians",
      "awayTeam": "Texas Rangers",
      "matchup": "Texas Rangers at Cleveland Guardians",
      "commenceTime": "2026-06-29T23:11:00Z",
      "slateDateEt": "2026-06-29",
      "homeScore": 3,
      "awayScore": 6,
      "winner": "Texas Rangers",
      "margin": 3,
      "totalRuns": 9,
      "completed": true,
      "status": "GRADED",
      "predictedWinner": "Texas Rangers",
      "predictedSide": "away",
      "score": "100",
      "winProbabilityPct": "95",
      "confidenceTier": "Premium",
      "tags": [
        "BOOK_DIVERGENCE",
        "REVERSAL",
        "RUN_LINE_MOVEMENT",
        "STEAM"
      ],
      "selectionBeforeWinnerOptimizer": null,
      "individualWinnerOptimized": null,
      "optimizerFlippedPick": null,
      "winnerOptimizer": null,
      "homeSignal": {
        "probStart": "0.57192",
        "probLatest": "0.16867",
        "side": "home",
        "averageAmericanOdds": "464.88",
        "bookCount": "8",
        "delta": "-0.40324",
        "latestGap": "0.66265",
        "runLineMovement": "-613.909",
        "team": "Cleveland Guardians",
        "tags": [
          "BOOK_DIVERGENCE",
          "RESISTANCE",
          "REVERSAL",
          "RUN_LINE_MOVEMENT"
        ],
        "score": "0",
        "winProbability": "0.05",
        "marketConsensusProbability": "0.16867",
        "bookDivergence": "0.05129",
        "reversalCount": "2",
        "winProbabilityPct": "5"
      },
      "awaySignal": {
        "probStart": "0.42808",
        "probLatest": "0.83133",
        "side": "away",
        "averageAmericanOdds": "-794.38",
        "bookCount": "8",
        "delta": "0.40324",
        "latestGap": "0.66265",
        "runLineMovement": "482.966",
        "team": "Texas Rangers",
        "tags": [
          "BOOK_DIVERGENCE",
          "REVERSAL",
          "RUN_LINE_MOVEMENT",
          "STEAM"
        ],
        "score": "100",
        "winProbability": "0.95",
        "marketConsensusProbability": "0.83133",
        "bookDivergence": "0.05129",
        "reversalCount": "2",
        "winProbabilityPct": "95"
      },
      "correct": true
    },
    {
      "id": "67d21f1e1c41537ef5b58b9abb1ff742",
      "gameKeyBase": "cincinnati reds|milwaukee brewers",
      "homeTeam": "Milwaukee Brewers",
      "awayTeam": "Cincinnati Reds",
      "matchup": "Cincinnati Reds at Milwaukee Brewers",
      "commenceTime": "2026-06-29T23:41:00Z",
      "slateDateEt": "2026-06-29",
      "homeScore": 5,
      "awayScore": 3,
      "winner": "Milwaukee Brewers",
      "margin": 2,
      "totalRuns": 8,
      "completed": true,
      "status": "GRADED",
      "predictedWinner": "Cincinnati Reds",
      "predictedSide": "away",
      "score": "100",
      "winProbabilityPct": "95",
      "confidenceTier": "Premium",
      "tags": [
        "BOOK_DIVERGENCE",
        "REVERSAL",
        "RUN_LINE_MOVEMENT",
        "STEAM"
      ],
      "selectionBeforeWinnerOptimizer": null,
      "individualWinnerOptimized": null,
      "optimizerFlippedPick": null,
      "winnerOptimizer": null,
      "homeSignal": {
        "probStart": "0.58204",
        "probLatest": "0.30994",
        "side": "home",
        "averageAmericanOdds": "211.88",
        "bookCount": "8",
        "delta": "-0.2721",
        "latestGap": "0.38012",
        "runLineMovement": "-185.716",
        "team": "Milwaukee Brewers",
        "tags": [
          "BOOK_DIVERGENCE",
          "RESISTANCE",
          "REVERSAL",
          "RUN_LINE_MOVEMENT"
        ],
        "score": "0",
        "winProbability": "0.05",
        "marketConsensusProbability": "0.30994",
        "bookDivergence": "0.169",
        "reversalCount": "4",
        "winProbabilityPct": "5"
      },
      "awaySignal": {
        "probStart": "0.41796",
        "probLatest": "0.69006",
        "side": "away",
        "averageAmericanOdds": "-291.12",
        "bookCount": "8",
        "delta": "0.2721",
        "latestGap": "0.38012",
        "runLineMovement": "101.398",
        "team": "Cincinnati Reds",
        "tags": [
          "BOOK_DIVERGENCE",
          "REVERSAL",
          "RUN_LINE_MOVEMENT",
          "STEAM"
        ],
        "score": "100",
        "winProbability": "0.95",
        "marketConsensusProbability": "0.69006",
        "bookDivergence": "0.169",
        "reversalCount": "4",
        "winProbabilityPct": "95"
      },
      "correct": false
    },
    {
      "id": "9e37d48efb8cc346ca1c01402049c4c0",
      "gameKeyBase": "san diego padres|chicago cubs",
      "homeTeam": "Chicago Cubs",
      "awayTeam": "San Diego Padres",
      "matchup": "San Diego Padres at Chicago Cubs",
      "commenceTime": "2026-06-30T00:06:00Z",
      "slateDateEt": "2026-06-29",
      "homeScore": 3,
      "awayScore": 2,
      "winner": "Chicago Cubs",
      "margin": 1,
      "totalRuns": 5,
      "completed": true,
      "status": "GRADED",
      "predictedWinner": "San Diego Padres",
      "predictedSide": "away",
      "score": "24.16",
      "winProbabilityPct": "10.4",
      "confidenceTier": "Pass",
      "tags": [
        "BOOK_DIVERGENCE",
        "REVERSAL",
        "RUN_LINE_MOVEMENT",
        "STEAM"
      ],
      "selectionBeforeWinnerOptimizer": null,
      "individualWinnerOptimized": null,
      "optimizerFlippedPick": null,
      "winnerOptimizer": null,
      "homeSignal": {
        "probStart": "0.58341",
        "probLatest": "0.52572",
        "side": "home",
        "averageAmericanOdds": "-103.38",
        "bookCount": "8",
        "delta": "-0.05769",
        "latestGap": "0.05144",
        "runLineMovement": "-83.75",
        "team": "Chicago Cubs",
        "tags": [
          "BOOK_DIVERGENCE",
          "RESISTANCE",
          "REVERSAL",
          "RUN_LINE_MOVEMENT"
        ],
        "score": "0",
        "winProbability": "0.05",
        "marketConsensusProbability": "0.52572",
        "bookDivergence": "0.15347",
        "reversalCount": "4",
        "winProbabilityPct": "5"
      },
      "awaySignal": {
        "probStart": "0.41659",
        "probLatest": "0.47428",
        "side": "away",
        "averageAmericanOdds": "46.38",
        "bookCount": "8",
        "delta": "0.05769",
        "latestGap": "0.05144",
        "runLineMovement": "23.216",
        "team": "San Diego Padres",
        "tags": [
          "BOOK_DIVERGENCE",
          "REVERSAL",
          "RUN_LINE_MOVEMENT",
          "STEAM"
        ],
        "score": "24.16",
        "winProbability": "0.104",
        "marketConsensusProbability": "0.47428",
        "bookDivergence": "0.15347",
        "reversalCount": "4",
        "winProbabilityPct": "10.4"
      },
      "correct": false
    },
    {
      "id": "ea976bf03d60b635db0b332eb5f79a0e",
      "gameKeyBase": "minnesota twins|houston astros",
      "homeTeam": "Houston Astros",
      "awayTeam": "Minnesota Twins",
      "matchup": "Minnesota Twins at Houston Astros",
      "commenceTime": "2026-06-30T00:11:00Z",
      "slateDateEt": "2026-06-29",
      "homeScore": 4,
      "awayScore": 5,
      "winner": "Minnesota Twins",
      "margin": 1,
      "totalRuns": 9,
      "completed": true,
      "status": "GRADED",
      "predictedWinner": "Minnesota Twins",
      "predictedSide": "away",
      "score": "100",
      "winProbabilityPct": "95",
      "confidenceTier": "Premium",
      "tags": [
        "REVERSAL",
        "RUN_LINE_MOVEMENT",
        "STEAM"
      ],
      "selectionBeforeWinnerOptimizer": null,
      "individualWinnerOptimized": null,
      "optimizerFlippedPick": null,
      "winnerOptimizer": null,
      "homeSignal": {
        "probStart": "0.55375",
        "probLatest": "0.1843",
        "side": "home",
        "averageAmericanOdds": "412",
        "bookCount": "8",
        "delta": "-0.36945",
        "latestGap": "0.6314",
        "runLineMovement": "-179.2",
        "team": "Houston Astros",
        "tags": [
          "RESISTANCE",
          "REVERSAL",
          "RUN_LINE_MOVEMENT"
        ],
        "score": "0",
        "winProbability": "0.05",
        "marketConsensusProbability": "0.1843",
        "bookDivergence": "0.03434",
        "reversalCount": "2",
        "winProbabilityPct": "5"
      },
      "awaySignal": {
        "probStart": "0.44625",
        "probLatest": "0.8157",
        "side": "away",
        "averageAmericanOdds": "-659.38",
        "bookCount": "8",
        "delta": "0.36945",
        "latestGap": "0.6314",
        "runLineMovement": "50.825",
        "team": "Minnesota Twins",
        "tags": [
          "REVERSAL",
          "RUN_LINE_MOVEMENT",
          "STEAM"
        ],
        "score": "100",
        "winProbability": "0.95",
        "marketConsensusProbability": "0.8157",
        "bookDivergence": "0.03434",
        "reversalCount": "2",
        "winProbabilityPct": "95"
      },
      "correct": true
    },
    {
      "id": "08c10b4a78eb4168d07c1e53f345d13f",
      "gameKeyBase": "miami marlins|colorado rockies",
      "homeTeam": "Colorado Rockies",
      "awayTeam": "Miami Marlins",
      "matchup": "Miami Marlins at Colorado Rockies",
      "commenceTime": "2026-06-30T00:41:00Z",
      "slateDateEt": "2026-06-29",
      "homeScore": 7,
      "awayScore": 10,
      "winner": "Miami Marlins",
      "margin": 3,
      "totalRuns": 17,
      "completed": true,
      "status": "GRADED",
      "predictedWinner": "Colorado Rockies",
      "predictedSide": "home",
      "score": "100",
      "winProbabilityPct": "95",
      "confidenceTier": "Premium",
      "tags": [
        "REVERSAL",
        "RUN_LINE_MOVEMENT",
        "STEAM"
      ],
      "selectionBeforeWinnerOptimizer": null,
      "individualWinnerOptimized": null,
      "optimizerFlippedPick": null,
      "winnerOptimizer": null,
      "homeSignal": {
        "probStart": "0.44588",
        "probLatest": "0.62654",
        "side": "home",
        "averageAmericanOdds": "-198.38",
        "bookCount": "8",
        "delta": "0.18066",
        "latestGap": "0.25309",
        "runLineMovement": "210.455",
        "team": "Colorado Rockies",
        "tags": [
          "REVERSAL",
          "RUN_LINE_MOVEMENT",
          "STEAM"
        ],
        "score": "100",
        "winProbability": "0.95",
        "marketConsensusProbability": "0.62654",
        "bookDivergence": "0.03059",
        "reversalCount": "1",
        "winProbabilityPct": "95"
      },
      "awaySignal": {
        "probStart": "0.55412",
        "probLatest": "0.37346",
        "side": "away",
        "averageAmericanOdds": "152.75",
        "bookCount": "8",
        "delta": "-0.18066",
        "latestGap": "0.25309",
        "runLineMovement": "-247.273",
        "team": "Miami Marlins",
        "tags": [
          "RESISTANCE",
          "REVERSAL",
          "RUN_LINE_MOVEMENT"
        ],
        "score": "0",
        "winProbability": "0.05",
        "marketConsensusProbability": "0.37346",
        "bookDivergence": "0.03059",
        "reversalCount": "1",
        "winProbabilityPct": "5"
      },
      "correct": false
    },
    {
      "id": "bc5ac70107417075ffd9dda7565caff3",
      "gameKeyBase": "san francisco giants|arizona diamondbacks",
      "homeTeam": "Arizona Diamondbacks",
      "awayTeam": "San Francisco Giants",
      "matchup": "San Francisco Giants at Arizona Diamondbacks",
      "commenceTime": "2026-06-30T01:41:00Z",
      "slateDateEt": "2026-06-29",
      "homeScore": 5,
      "awayScore": 4,
      "winner": "Arizona Diamondbacks",
      "margin": 1,
      "totalRuns": 9,
      "completed": true,
      "status": "GRADED",
      "predictedWinner": "Arizona Diamondbacks",
      "predictedSide": "home",
      "score": "43.79",
      "winProbabilityPct": "37.34",
      "confidenceTier": "Pass",
      "tags": [
        "BOOK_AGREEMENT",
        "REVERSAL"
      ],
      "selectionBeforeWinnerOptimizer": null,
      "individualWinnerOptimized": null,
      "optimizerFlippedPick": null,
      "winnerOptimizer": null,
      "homeSignal": {
        "probStart": "0.55377",
        "probLatest": "0.55109",
        "side": "home",
        "averageAmericanOdds": "-134",
        "bookCount": "11",
        "delta": "-0.00268",
        "latestGap": "0.10218",
        "runLineMovement": "2.636",
        "team": "Arizona Diamondbacks",
        "tags": [
          "BOOK_AGREEMENT",
          "REVERSAL"
        ],
        "score": "43.79",
        "winProbability": "0.3734",
        "marketConsensusProbability": "0.55109",
        "bookDivergence": "0.01705",
        "reversalCount": "2",
        "winProbabilityPct": "37.34"
      },
      "awaySignal": {
        "probStart": "0.44623",
        "probLatest": "0.44891",
        "side": "away",
        "averageAmericanOdds": "114.45",
        "bookCount": "11",
        "delta": "0.00268",
        "latestGap": "0.10218",
        "runLineMovement": "-3",
        "team": "San Francisco Giants",
        "tags": [
          "BOOK_AGREEMENT",
          "REVERSAL"
        ],
        "score": "38.35",
        "winProbability": "0.2747",
        "marketConsensusProbability": "0.44891",
        "bookDivergence": "0.01705",
        "reversalCount": "2",
        "winProbabilityPct": "27.47"
      },
      "correct": true
    },
    {
      "id": "a898264b051f27a33274cbdacc554c46",
      "gameKeyBase": "los angeles dodgers|athletics",
      "homeTeam": "Athletics",
      "awayTeam": "Los Angeles Dodgers",
      "matchup": "Los Angeles Dodgers at Athletics",
      "commenceTime": "2026-06-30T01:41:00Z",
      "slateDateEt": "2026-06-29",
      "homeScore": 4,
      "awayScore": 9,
      "winner": "Los Angeles Dodgers",
      "margin": 5,
      "totalRuns": 13,
      "completed": true,
      "status": "GRADED",
      "predictedWinner": "Athletics",
      "predictedSide": "home",
      "score": "43.67",
      "winProbabilityPct": "37.11",
      "confidenceTier": "Pass",
      "tags": [
        "BOOK_AGREEMENT",
        "COMPRESSED_MARKET",
        "REVERSAL"
      ],
      "selectionBeforeWinnerOptimizer": null,
      "individualWinnerOptimized": null,
      "optimizerFlippedPick": null,
      "winnerOptimizer": null,
      "homeSignal": {
        "probStart": "0.47426",
        "probLatest": "0.47834",
        "side": "home",
        "averageAmericanOdds": "46.45",
        "bookCount": "11",
        "delta": "0.00407",
        "latestGap": "0.04333",
        "runLineMovement": "-2",
        "team": "Athletics",
        "tags": [
          "BOOK_AGREEMENT",
          "COMPRESSED_MARKET",
          "REVERSAL"
        ],
        "score": "43.67",
        "winProbability": "0.3711",
        "marketConsensusProbability": "0.47834",
        "bookDivergence": "0.0105",
        "reversalCount": "2",
        "winProbabilityPct": "37.11"
      },
      "awaySignal": {
        "probStart": "0.52574",
        "probLatest": "0.52166",
        "side": "away",
        "averageAmericanOdds": "-118.64",
        "bookCount": "11",
        "delta": "-0.00407",
        "latestGap": "0.04333",
        "runLineMovement": "1.545",
        "team": "Los Angeles Dodgers",
        "tags": [
          "BOOK_AGREEMENT",
          "COMPRESSED_MARKET",
          "REVERSAL"
        ],
        "score": "41.87",
        "winProbability": "0.3368",
        "marketConsensusProbability": "0.52166",
        "bookDivergence": "0.0105",
        "reversalCount": "2",
        "winProbabilityPct": "33.68"
      },
      "correct": false
    },
    {
      "id": "0ce57b4f423d4bee56a8b4b941856426",
      "gameKeyBase": "los angeles angels|seattle mariners",
      "homeTeam": "Seattle Mariners",
      "awayTeam": "Los Angeles Angels",
      "matchup": "Los Angeles Angels at Seattle Mariners",
      "commenceTime": "2026-06-30T01:41:00Z",
      "slateDateEt": "2026-06-29",
      "homeScore": 6,
      "awayScore": 2,
      "winner": "Seattle Mariners",
      "margin": 4,
      "totalRuns": 8,
      "completed": true,
      "status": "GRADED",
      "predictedWinner": "Los Angeles Angels",
      "predictedSide": "away",
      "score": "44.03",
      "winProbabilityPct": "37.81",
      "confidenceTier": "Pass",
      "tags": [
        "BOOK_AGREEMENT",
        "REVERSAL",
        "RUN_LINE_CONFIRMATION",
        "RUN_LINE_MOVEMENT",
        "STEAM"
      ],
      "selectionBeforeWinnerOptimizer": null,
      "individualWinnerOptimized": null,
      "optimizerFlippedPick": null,
      "winnerOptimizer": null,
      "homeSignal": {
        "probStart": "0.65938",
        "probLatest": "0.64262",
        "side": "home",
        "averageAmericanOdds": "-201.55",
        "bookCount": "11",
        "delta": "-0.01677",
        "latestGap": "0.28523",
        "runLineMovement": "137.545",
        "team": "Seattle Mariners",
        "tags": [
          "BOOK_AGREEMENT",
          "RESISTANCE",
          "REVERSAL",
          "RUN_LINE_MOVEMENT"
        ],
        "score": "43.22",
        "winProbability": "0.3624",
        "marketConsensusProbability": "0.64262",
        "bookDivergence": "0.01297",
        "reversalCount": "2",
        "winProbabilityPct": "36.24"
      },
      "awaySignal": {
        "probStart": "0.34062",
        "probLatest": "0.35738",
        "side": "away",
        "averageAmericanOdds": "169.18",
        "bookCount": "11",
        "delta": "0.01677",
        "latestGap": "0.28523",
        "runLineMovement": "-11.455",
        "team": "Los Angeles Angels",
        "tags": [
          "BOOK_AGREEMENT",
          "REVERSAL",
          "RUN_LINE_CONFIRMATION",
          "RUN_LINE_MOVEMENT",
          "STEAM"
        ],
        "score": "44.03",
        "winProbability": "0.3781",
        "marketConsensusProbability": "0.35738",
        "bookDivergence": "0.01297",
        "reversalCount": "2",
        "winProbabilityPct": "37.81"
      },
      "correct": false
    }
  ],
  "policy": "Audit every completed MLB game in the trailing 24 hours. The optimizer target is correct team-winner selection for every individual game; 90% is measured as rolling 24h accuracy across all optimized picks.",
  "stored": {
    "ok": true,
    "latestPk": "MLB_ROLLING_24H_AUDIT#LATEST",
    "latestSk": "LATEST",
    "runPk": "MLB_ROLLING_24H_AUDIT#RUNS",
    "runSk": "AUDIT#2026-06-30T14:27:06.872501+00:00"
  }
}
