{
  "blockers": [],
  "createdAtEt": "2026-07-23T11:27:10.531708-04:00",
  "createdAtUtc": "2026-07-23T15:27:10.531708Z",
  "games": [
    {
      "awayTeam": "San Diego Padres",
      "commenceTime": "2026-07-23T16:15:00+00:00",
      "confidenceTier": "Pass",
      "fundamentalsState": "NOT_APPLIED",
      "gameIdentity": "official:824893",
      "homeTeam": "Atlanta Braves",
      "hotDelta": 0.000411,
      "hotTeam": "Atlanta Braves",
      "latestMovementAtUtc": "2026-07-23T15:15:26.804272+00:00",
      "movementFeaturePresent": true,
      "movementStrength": "LOW",
      "officialGamePk": "824893",
      "predictedWinner": "Atlanta Braves",
      "predictionPresent": true,
      "predictionScore": 5.78,
      "scoreableMoneylineObserved": true
    },
    {
      "awayTeam": "Minnesota Twins",
      "commenceTime": "2026-07-23T17:10:00+00:00",
      "confidenceTier": "Pass",
      "fundamentalsState": "NOT_APPLIED",
      "gameIdentity": "official:824406",
      "homeTeam": "Cleveland Guardians",
      "hotDelta": 0.002299,
      "hotTeam": "Cleveland Guardians",
      "latestMovementAtUtc": "2026-07-23T15:15:26.804272+00:00",
      "movementFeaturePresent": true,
      "movementStrength": "LOW",
      "officialGamePk": "824406",
      "predictedWinner": "Cleveland Guardians",
      "predictionPresent": true,
      "predictionScore": 42.35,
      "scoreableMoneylineObserved": true
    },
    {
      "awayTeam": "Tampa Bay Rays",
      "commenceTime": "2026-07-23T19:07:00+00:00",
      "confidenceTier": "Coin Flip",
      "fundamentalsState": "NOT_APPLIED",
      "gameIdentity": "official:822785",
      "homeTeam": "Toronto Blue Jays",
      "hotDelta": 0.001093,
      "hotTeam": "Tampa Bay Rays",
      "latestMovementAtUtc": "2026-07-23T15:15:26.804272+00:00",
      "movementFeaturePresent": true,
      "movementStrength": "LOW",
      "officialGamePk": "822785",
      "predictedWinner": "Tampa Bay Rays",
      "predictionPresent": true,
      "predictionScore": 53.59,
      "scoreableMoneylineObserved": true
    },
    {
      "awayTeam": "Arizona Diamondbacks",
      "commenceTime": "2026-07-23T21:15:00+00:00",
      "confidenceTier": "Pass",
      "fundamentalsState": "NOT_APPLIED",
      "gameIdentity": "official:823042",
      "homeTeam": "St. Louis Cardinals",
      "hotDelta": 0.000758,
      "hotTeam": "Arizona Diamondbacks",
      "latestMovementAtUtc": "2026-07-23T15:15:26.804272+00:00",
      "movementFeaturePresent": true,
      "movementStrength": "LOW",
      "officialGamePk": "823042",
      "predictedWinner": "St. Louis Cardinals",
      "predictionPresent": true,
      "predictionScore": 18.14,
      "scoreableMoneylineObserved": true
    },
    {
      "awayTeam": "Kansas City Royals",
      "commenceTime": "2026-07-23T22:40:00+00:00",
      "confidenceTier": "Pass",
      "fundamentalsState": "NOT_APPLIED",
      "gameIdentity": "official:824247",
      "homeTeam": "Detroit Tigers",
      "hotDelta": 0.000519,
      "hotTeam": "Detroit Tigers",
      "latestMovementAtUtc": "2026-07-23T15:15:26.804272+00:00",
      "movementFeaturePresent": true,
      "movementStrength": "LOW",
      "officialGamePk": "824247",
      "predictedWinner": "Detroit Tigers",
      "predictionPresent": true,
      "predictionScore": 41.48,
      "scoreableMoneylineObserved": true
    }
  ],
  "guardPassed": true,
  "missingMovementGameIdentities": [],
  "missingPredictionGameIdentities": [],
  "ok": true,
  "proofType": "MLB_SCORING_GUARD_READ_ONLY_PROOF",
  "readOnly": true,
  "rosterAuthority": {
    "fingerprint": "7f7230ef73f3c9f9ebab5a0373a91efb6b503483a4e48d8bad6e14b74940ed6d",
    "gameCount": 5,
    "observedAtUtc": "2026-07-23T15:15:26.804272+00:00",
    "officialScheduleBacked": true,
    "pullId": "mlb_v1_2026-07-23_2026_07_23T15_15_26_804272_00_00"
  },
  "secretExposed": false,
  "slateDateEt": "2026-07-23",
  "sourceOfTruth": {
    "canonicalPullPartition": "PULLS#mlb#2026-07-23",
    "movementPartition": "ML_FEATURE#mlb#2026-07-23",
    "predictionPartition": "GAME_WINNERS#mlb#2026-07-23"
  },
  "summary": {
    "canonicalPullCount": 42,
    "fundamentalsAppliedCount": 0,
    "fundamentalsNotAppliedOrMissingCount": 5,
    "latestCanonicalPullAtUtc": "2026-07-23T15:15:26.804272+00:00",
    "missingMovementCount": 0,
    "missingPredictionCount": 0,
    "movementFeatureGameCount": 5,
    "officialGameCount": 5,
    "persistedPredictionGameCount": 5,
    "scoreableGameCount": 5
  },
  "version": "MLB-SCORING-GUARD-v1-output-side-coverage"
}
